embeddings_evaluator/__init__.py
embeddings_evaluator/comparison.py
embeddings_evaluator/loaders.py
embeddings_evaluator/metrics.py
embeddings_evaluator/metrics_optimized.py
embeddings_evaluator-1.0.1.dist-info/licenses/LICENSE
embeddings_evaluator-1.0.1.dist-info/METADATA
embeddings_evaluator-1.0.1.dist-info/WHEEL
embeddings_evaluator-1.0.1.dist-info/top_level.txt
embeddings_evaluator-1.0.1.dist-info/RECORD
