Metadata-Version: 2.4
Name: embeddings_evaluator
Version: 1.0.1
Summary: Tool for analyzing and comparing embedding models through pairwise cosine similarity distributions
Home-page: https://github.com/vinerya/embeddings_evaluator
Author: Moudather Chelbi
Author-email: moudather.chelbi@gmail.com
Keywords: embeddings,similarity,evaluation,faiss,visualization
Classifier: Development Status :: 5 - Production/Stable
Classifier: Intended Audience :: Science/Research
Classifier: Topic :: Scientific/Engineering :: Artificial Intelligence
Classifier: License :: OSI Approved :: MIT License
Classifier: Programming Language :: Python :: 3
Classifier: Programming Language :: Python :: 3.8
Classifier: Programming Language :: Python :: 3.9
Classifier: Programming Language :: Python :: 3.10
Requires-Python: >=3.8
License-File: LICENSE
Requires-Dist: numpy>=1.23.5
Requires-Dist: pandas>=1.5.3
Requires-Dist: plotly>=5.14.1
Requires-Dist: scipy>=1.10.1
Requires-Dist: scikit-learn>=1.2.0
Requires-Dist: faiss-cpu
Requires-Dist: qdrant-client>=1.7.0
Requires-Dist: matplotlib>=3.5.0
Dynamic: author
Dynamic: author-email
Dynamic: classifier
Dynamic: description
Dynamic: description-content-type
Dynamic: home-page
Dynamic: keywords
Dynamic: license-file
Dynamic: requires-dist
Dynamic: requires-python
Dynamic: summary
